my_feature_package/__init__.py
my_feature_package/text_formatter.py
my_feature_package/validator.py
my_feature_package-0.1.0.dist-info/METADATA
my_feature_package-0.1.0.dist-info/WHEEL
my_feature_package-0.1.0.dist-info/top_level.txt
my_feature_package-0.1.0.dist-info/RECORD
