Metadata-Version: 2.4
Name: my-feature-package
Version: 0.1.0
Summary: Text formatting and validation utilities
Home-page: https://github.com/yourusername/my-feature-package
Author: Your Name
Author-email: your.email@example.com
Project-URL: Bug Reports, https://github.com/yourusername/my-feature-package/issues
Project-URL: Source, https://github.com/yourusername/my-feature-package
Keywords: text formatting,validation,text processing,utilities
Classifier: Development Status :: 3 - Alpha
Classifier: Intended Audience :: Developers
Classifier: License :: OSI Approved :: MIT License
Classifier: Operating System :: OS Independent
Classifier: Programming Language :: Python :: 3
Classifier: Programming Language :: Python :: 3.8
Classifier: Programming Language :: Python :: 3.9
Classifier: Programming Language :: Python :: 3.10
Classifier: Programming Language :: Python :: 3.11
Classifier: Programming Language :: Python :: 3.12
Classifier: Programming Language :: Python :: 3.13
Requires-Python: >=3.8
Dynamic: author
Dynamic: author-email
Dynamic: classifier
Dynamic: description
Dynamic: description-content-type
Dynamic: home-page
Dynamic: keywords
Dynamic: project-url
Dynamic: requires-python
Dynamic: summary
